short_unique_id/__init__.py
short_unique_id/short_id.py
short_unique_id/snowflake.py
short_unique_id-0.2.1.dist-info/LICENSE
short_unique_id-0.2.1.dist-info/METADATA
short_unique_id-0.2.1.dist-info/WHEEL
short_unique_id-0.2.1.dist-info/RECORD
