Metadata-Version: 2.3
Name: short-unique-id
Version: 0.2.1
Summary: Tiny, dependency-free Snowflake-style and random short ID generator for Python.
License: MIT
Keywords: shortid,short-id,snowflake,uuid,unique-id,identifier
Author: Purushot14
Author-email: prakash.purushot@gmail.com
Requires-Python: >=3.9
Classifier: Development Status :: 4 - Beta
Classifier: Intended Audience :: Developers
Classifier: License :: OSI Approved :: MIT License
Classifier: Programming Language :: Python :: 3
Classifier: Programming Language :: Python :: 3.9
Classifier: Programming Language :: Python :: 3.10
Classifier: Programming Language :: Python :: 3.11
Classifier: Programming Language :: Python :: 3.12
Classifier: Programming Language :: Python :: 3.13
Classifier: Programming Language :: Python :: 3 :: Only
Classifier: Topic :: Software Development :: Libraries :: Python Modules
Classifier: Topic :: Utilities
Project-URL: Documentation, https://github.com/Purushot14/short-unique-id#readme
Project-URL: Homepage, https://github.com/Purushot14/short-unique-id
Project-URL: Repository, https://github.com/Purushot14/short-unique-id
